Metadata-Version: 2.1
Name: odoo-addon-companyweb_base
Version: 18.0.1.1.2
Requires-Python: >=3.10
Requires-Dist: odoo==18.0.*
Requires-Dist: zeep
Summary: Know who you are dealing with. Enhance Odoo partner data from companyweb.be.
Home-page: https://github.com/OCA/l10n-belgium
License: AGPL-3
Author: ACSONE SA/NV,Odoo Community Association (OCA)
Author-email: support@odoo-community.org
Classifier: Programming Language :: Python
Classifier: Framework :: Odoo
Classifier: Framework :: Odoo :: 18.0
Classifier: License :: OSI Approved :: GNU Affero General Public License v3
Classifier: Development Status :: 5 - Production/Stable
